setup.py
laas/__init__.py
python_laas.egg-info/PKG-INFO
python_laas.egg-info/SOURCES.txt
python_laas.egg-info/dependency_links.txt
python_laas.egg-info/not-zip-safe
python_laas.egg-info/requires.txt
python_laas.egg-info/top_level.txt