Metadata-Version: 1.0
Name: python-laas
Version: 0.1.0
Summary: Handy tools required to format your Python logs for LaaS/Splunk ingestion.
Home-page: https://bitbucket.org/atlassianlabs/python-laas
Author: Christopher Carter
Author-email: chcarter@atlassian.com
License: MIT
Platform: UNKNOWN
